wolsey/__init__.py
wolsey/wolsey.py
wolsey-0.0.1.data/scripts/wol-lsf_copy_files.py
wolsey-0.0.1.data/scripts/wol-summarize_log.py
wolsey-0.0.1.data/scripts/wol-summary_executions.py
wolsey-0.0.1.dist-info/LICENSE.txt
wolsey-0.0.1.dist-info/METADATA
wolsey-0.0.1.dist-info/WHEEL
wolsey-0.0.1.dist-info/top_level.txt
wolsey-0.0.1.dist-info/RECORD
