Metadata-Version: 2.1
Name: wolsey
Version: 0.0.1
Summary: wolsey - utilities for Cromwell
Home-page: UNKNOWN
Author: 
Author-email: 
License: MIT
Platform: UNKNOWN
Provides-Extra: dev
Requires-Dist: pytest; extra == 'dev'
Requires-Dist: tox; extra == 'dev'
